README.md
setup.py
pyearl/__init__.py
pyearl/core.py
pyearl/db.py
pyearl/exceptions.py
pyearl/route.py
pyearl/session.py
pyearl/template.py
pyearl/wsgi_app.py
pyearl/wsgi_server.py
pyearl.egg-info/PKG-INFO
pyearl.egg-info/SOURCES.txt
pyearl.egg-info/dependency_links.txt
pyearl.egg-info/entry_points.txt
pyearl.egg-info/requires.txt
pyearl.egg-info/top_level.txt