Metadata-Version: 1.0
Name: pyearl
Version: 0.0.1
Summary: 一个简单的 Python 框架
Home-page: https://github.com/lim-mil/pyearl
Author: limyel
Author-email: limyel@qq.com
License: UNKNOWN
Platform: UNKNOWN
